[
  {
    "Id": 1,
    "FullName": "Ekremi Canbehan Nihat Celal",
    "LastSeen": "10.03.22",
    "Activity": 0,
    "TestScore": 0,
    "ClassworkScore": 0,
    "Crystals": 0,
    "Comment": ""
  },
  {
    "Id": 2,
    "FullName": "Ekremi Canbehan Nihat Celal",
    "LastSeen": "10.03.22",
    "Activity": 0,
    "TestScore": 0,
    "ClassworkScore": 0,
    "Crystals": 0,
    "Comment": ""
  },
  {
    "Id": 3,
    "FullName": "Ekremi Canbehan Nihat Celal",
    "LastSeen": "10.03.22",
    "Activity": 0,
    "TestScore": 0,
    "ClassworkScore": 0,
    "Crystals": 0,
    "Comment": ""
  },
  {
    "Id": 4,
    "FullName": "Ekremi Canbehan Nihat Celal",
    "LastSeen": "10.03.22",
    "Activity": 0,
    "TestScore": 0,
    "ClassworkScore": 0,
    "Crystals": 0,
    "Comment": ""
  },
  {
    "Id": 5,
    "FullName": "Ekremi Canbehan Nihat Celal",
    "LastSeen": "10.03.22",
    "Activity": 0,
    "TestScore": 0,
    "ClassworkScore": 0,
    "Crystals": 0,
    "Comment": ""
  },
  {
    "Id": 6,
    "FullName": "Ekremi Canbehan Nihat Celal",
    "LastSeen": "10.03.22",
    "Activity": 0,
    "TestScore": 0,
    "ClassworkScore": 0,
    "Crystals": 0,
    "Comment": ""
  },
  {
    "Id": 7,
    "FullName": "Ekremi Canbehan Nihat Celal",
    "LastSeen": "10.03.22",
    "Activity": 0,
    "TestScore": 0,
    "ClassworkScore": 0,
    "Crystals": 0,
    "Comment": ""
  },
  {
    "Id": 8,
    "FullName": "Ekremi Canbehan Nihat Celal",
    "LastSeen": "10.03.22",
    "Activity": 0,
    "TestScore": 0,
    "ClassworkScore": 0,
    "Crystals": 0,
    "Comment": ""
  },
  {
    "Id": 9,
    "FullName": "Ekremi Canbehan Nihat Celal",
    "LastSeen": "10.03.22",
    "Activity": 0,
    "TestScore": 0,
    "ClassworkScore": 0,
    "Crystals": 0,
    "Comment": ""
  }
]